safescope/__init__.py
safescope/side_scope.py
safescope/src.py
safescope-0.2.6.dist-info/LICENSE
safescope-0.2.6.dist-info/METADATA
safescope-0.2.6.dist-info/WHEEL
safescope-0.2.6.dist-info/top_level.txt
safescope-0.2.6.dist-info/RECORD
