Metadata-Version: 2.1
Name: safescope
Version: 0.2.6
Summary: Python package for preventing use of variables from global scope.
Home-page: https://github.com/havakv/safescope
Author: Haavard Kvamme
Author-email: haavard.kvamme@gmail.com
License: BSD license
Keywords: safescope
Platform: UNKNOWN
Classifier: Development Status :: 2 - Pre-Alpha
Classifier: Intended Audience :: Developers
Classifier: License :: OSI Approved :: BSD License
Classifier: Natural Language :: English
Classifier: Programming Language :: Python :: 3.7
Classifier: Programming Language :: Python :: 3.6
Classifier: Programming Language :: Python :: 3.5
Requires-Python: >=3.5
